opencos/__init__.py
opencos/_version.py
opencos/_waves_pkg.sv
opencos/deps_schema.py
opencos/eda.py
opencos/eda_base.py
opencos/eda_config.py
opencos/eda_config_defaults.yml
opencos/eda_config_reduced.yml
opencos/eda_deps_bash_completion.bash
opencos/eda_deps_sanitize.py
opencos/eda_extract_targets.py
opencos/eda_tool_helper.py
opencos/export_helper.py
opencos/export_json_convert.py
opencos/files.py
opencos/names.py
opencos/peakrdl_cleanup.py
opencos/seed.py
opencos/util.py
opencos/commands/__init__.py
opencos/commands/build.py
opencos/commands/deps_help.py
opencos/commands/elab.py
opencos/commands/export.py
opencos/commands/flist.py
opencos/commands/lec.py
opencos/commands/lint.py
opencos/commands/multi.py
opencos/commands/open.py
opencos/commands/proj.py
opencos/commands/shell.py
opencos/commands/sim.py
opencos/commands/sweep.py
opencos/commands/synth.py
opencos/commands/targets.py
opencos/commands/upload.py
opencos/commands/waves.py
opencos/deps/__init__.py
opencos/deps/defaults.py
opencos/deps/deps_commands.py
opencos/deps/deps_file.py
opencos/deps/deps_processor.py
opencos/docs/Architecture.md
opencos/docs/ConnectingApps.md
opencos/docs/DEPS.md
opencos/docs/Debug.md
opencos/docs/DirectoryStructure.md
opencos/docs/Installation.md
opencos/docs/OcVivadoTcl.md
opencos/docs/OpenQuestions.md
opencos/docs/README.md
opencos/docs/RtlCodingStyle.md
opencos/docs/eda.md
opencos/docs/oc_cli.md
opencos/hw/__init__.py
opencos/hw/oc_cli.py
opencos/hw/pcie.py
opencos/tools/__init__.py
opencos/tools/cocotb.py
opencos/tools/invio.py
opencos/tools/invio_helpers.py
opencos/tools/invio_yosys.py
opencos/tools/iverilog.py
opencos/tools/modelsim_ase.py
opencos/tools/quartus.py
opencos/tools/questa.py
opencos/tools/questa_common.py
opencos/tools/questa_fe.py
opencos/tools/questa_fse.py
opencos/tools/riviera.py
opencos/tools/slang.py
opencos/tools/slang_yosys.py
opencos/tools/surelog.py
opencos/tools/tabbycad_yosys.py
opencos/tools/verilator.py
opencos/tools/vivado.py
opencos_eda-0.3.13.dist-info/licenses/LICENSE
opencos_eda-0.3.13.dist-info/licenses/LICENSE.spdx
opencos_eda-0.3.13.dist-info/METADATA
opencos_eda-0.3.13.dist-info/WHEEL
opencos_eda-0.3.13.dist-info/entry_points.txt
opencos_eda-0.3.13.dist-info/top_level.txt
opencos_eda-0.3.13.dist-info/RECORD
