Metadata-Version: 2.4
Name: opencos-eda
Version: 0.3.13
Summary: A simple Python package for wrapping RTL simuliatons and synthesis
Author-email: Simon Sabato <simon@cognichip.ai>, Drew Ranck <drew@cognichip.ai>
Project-URL: Homepage, https://github.com/cognichip/opencos
Requires-Python: >=3.8
License-File: LICENSE
License-File: LICENSE.spdx
Requires-Dist: mergedeep>=1.3.4
Requires-Dist: peakrdl>=1.1.0
Requires-Dist: psutil>=7.0.0
Requires-Dist: pyyaml>=6.0.2
Requires-Dist: python-dotenv>=1.0.1
Requires-Dist: schema>=0.7.7
Requires-Dist: toml>=0.10.2
Requires-Dist: yamllint>=1.35.1
Requires-Dist: PySerial>=3.5
Requires-Dist: supports_color>=0.2.0
Provides-Extra: dev
Requires-Dist: pylint>=3.0.0; extra == "dev"
Requires-Dist: pytest>=8.3.5; extra == "dev"
Provides-Extra: cocotb
Requires-Dist: cocotb>=2.0; extra == "cocotb"
Requires-Dist: pytest>=8.3.5; extra == "cocotb"
Requires-Dist: coverage>=7.6.1; extra == "cocotb"
Provides-Extra: docs
Requires-Dist: mkdocs; extra == "docs"
Requires-Dist: mkdocs-material; extra == "docs"
Requires-Dist: mkdocs-wavedrom-plugin; extra == "docs"
Requires-Dist: mkdocs-plantuml; extra == "docs"
Dynamic: license-file
